{
  "fee_structure": {
    "currency": "PKR",
    "academic_year": "2024-25",
    "fees": [
      {
        "fee_type": "Admission Fee",
        "amount": 5000,
        "description": "One-time admission processing fee",
        "applicable_to": "all_programs"
      },
      {
        "fee_type": "Tuition Fee (Per Semester)",
        "amount": 25000,
        "description": "Semester tuition fee",
        "applicable_to": "all_programs"
      },
      {
        "fee_type": "Examination Fee",
        "amount": 2000,
        "description": "Per semester examination fee",
        "applicable_to": "all_programs"
      },
      {
        "fee_type": "Library Fee",
        "amount": 1000,
        "description": "Annual library membership fee",
        "applicable_to": "all_programs"
      },
      {
        "fee_type": "Hostel Fee (Monthly)",
        "amount": 15000,
        "description": "Monthly hostel accommodation fee",
        "applicable_to": "all_programs",
        "optional": true
      },
      {
        "fee_type": "Transport Fee (Monthly)",
        "amount": 5000,
        "description": "Monthly transport service fee",
        "applicable_to": "all_programs",
        "optional": true
      },
      {
        "fee_type": "Lab Fee",
        "amount": 3000,
        "description": "Per semester laboratory fee",
        "applicable_to": "practical_programs"
      },
      {
        "fee_type": "Uniform Fee",
        "amount": 2000,
        "description": "One-time uniform fee",
        "applicable_to": "all_programs"
      }
    ],
    "payment_schedule": {
      "admission_fee": "on_admission",
      "tuition_fee": "per_semester",
      "examination_fee": "per_semester",
      "library_fee": "annually",
      "hostel_fee": "monthly",
      "transport_fee": "monthly",
      "lab_fee": "per_semester",
      "uniform_fee": "on_admission"
    }
  }
}
